multiplier.v
// Problem: only takes in one cycle of inputs and stops.

module BinaryMultiplicationPartialSum
#(
  parameter BIT_WIDTH = 8,
  parameter OUTPUTBITWIDTH = BIT_WIDTH  * 2
)(
  input clk,
  input in,
  input reset, // high reset
  input [BIT_WIDTH-1:0] M, Q,
  output [OUTPUTBITWIDTH-1:0] out,
  output done
);

parameter idle = 2'b00, check = 2'b01, DONE = 2'b11;
reg [BIT_WIDTH-1:0] Q_reg;
reg [BIT_WIDTH-1:0] M_reg;
reg [OUTPUTBITWIDTH-1:0] out_reg;
reg [1:0] state, next_state; 
reg [BIT_WIDTH:0] cycle_count;
reg [OUTPUTBITWIDTH-1:0] temp_out;

always @(*) begin
  case(state)
    idle: next_state = in ? check : idle;
    check: next_state = (cycle_count == BIT_WIDTH) ? DONE : check;
    DONE: next_state = idle;
    default: next_state = idle;
  endcase
end

always @(posedge clk, posedge reset) begin
  if (reset) begin  
    state <= 0; 
    Q_reg <= 0;
    M_reg <= 0;
    cycle_count <= 0;
  end
  else begin 
    state <= next_state; 
    if (state == idle && in) begin
        Q_reg <= Q;
        M_reg <= M;
        out_reg <= 0;
        cycle_count <= 0;
      end
    else if (state == check && cycle_count < BIT_WIDTH) begin
        if (Q_reg[0] == 1'b1) begin 
          temp_out = {out_reg[OUTPUTBITWIDTH-1:BIT_WIDTH] + M_reg, out_reg[BIT_WIDTH-1:0]};
        end else begin
          temp_out = out_reg;
        end
        out_reg <= temp_out >> 1;
        cycle_count <= cycle_count + 1;
        Q_reg <= Q_reg >> 1;
    end
  end
end

assign done = (state == DONE) ? 1'b1 : 1'b0;
assign out = out_reg;

endmodule

BinaryMultiplicationPartialSumTestBench.v
module testbench;
parameter BIT_WIDTH = 8;
parameter OUTPUTBITWIDTH = BIT_WIDTH * 2;
reg clk, reset, in;
reg [BIT_WIDTH-1:0] M, Q;
wire [OUTPUTBITWIDTH-1:0] out;
wire done;

BinaryMultiplicationPartialSum #(
  .BIT_WIDTH(BIT_WIDTH), 
  .OUTPUTBITWIDTH(OUTPUTBITWIDTH)
) inst1 (
  .in(in), 
  .clk(clk), 
  .reset(reset), 
  .M(M), 
  .Q(Q), 
  .out(out), 
  .done(done)
);

// Name by instantiation .inner_module(out_module)
always #5 clk = ~clk;
initial begin
  $dumpfile("BinaryMultiplicationPartialSumTestBench.vcd");
  $dumpvars(0, testbench);
  $monitor($time,"clk=%b, reset=%b, in=%b, M=%b, Q=%b, out=%b, done=%b", clk, reset, in, M, Q, out, done);
  reset = 1; clk = 0; reset = 1; in = 0; M = 8'b00000000; Q = 8'b00000000;
  #5 reset = 0; in = 1; M = 8'b01010111; Q = 8'b01010111; //  01110110010001 (7569)
  #5 in = 1;
  #5 in = 0;
  #100 $finish;
end

endmodule

BinaryMultiplicationPartialSumTestBench.vcd
$date
	Sun Sep 27 14:03:36 2026
$end
$version
	Icarus Verilog
$end
$timescale
	1s
$end
$scope module testbench $end
$var wire 16 ! out [15:0] $end
$var wire 1 " done $end
$var parameter 32 # BIT_WIDTH $end
$var parameter 64 $ OUTPUTBITWIDTH $end
$var reg 8 % M [7:0] $end
$var reg 8 & Q [7:0] $end
$var reg 1 ' clk $end
$var reg 1 ( in $end
$var reg 1 ) reset $end
$scope module inst1 $end
$var wire 8 * M [7:0] $end
$var wire 8 + Q [7:0] $end
$var wire 1 ' clk $end
$var wire 1 ( in $end
$var wire 16 , out [15:0] $end
$var wire 1 ) reset $end
$var wire 1 " done $end
$var parameter 32 - BIT_WIDTH $end
$var parameter 2 . DONE $end
$var parameter 64 / OUTPUTBITWIDTH $end
$var parameter 2 0 check $end
$var parameter 2 1 idle $end
$var reg 8 2 M_reg [7:0] $end
$var reg 8 3 Q_reg [7:0] $end
$var reg 9 4 cycle_count [8:0] $end
$var reg 2 5 next_state [1:0] $end
$var reg 16 6 out_reg [15:0] $end
$var reg 2 7 state [1:0] $end
$var reg 16 8 temp_out [15:0] $end
$upscope $end
$upscope $end
$enddefinitions $end
$comment Show the parameter values. $end
$dumpall
b0 1
b1 0
b10000 /
b11 .
b1000 -
b10000 $
b1000 #
$end
#0
$dumpvars
bx 8
b0 7
bx 6
b0 5
b0 4
b0 3
b0 2
bx ,
b0 +
b0 *
1)
0(
0'
b0 &
b0 %
0"
bx !
$end
#5
b0 !
b0 ,
b0 6
b1010111 2
b1010111 3
b1 5
b1010111 &
b1010111 +
b1010111 %
b1010111 *
1(
0)
1'
#10
0'
#15
b1 7
b1 5
0(
1'
#20
0'
#25
b101011 3
b1 4
b10101110000000 !
b10101110000000 ,
b10101110000000 6
b101011100000000 8
1'
#30
0'
#35
b10101 3
b10 4
b100000101000000 !
b100000101000000 ,
b100000101000000 6
b1000001010000000 8
1'
#40
0'
#45
b1010 3
b11 4
b100110000100000 !
b100110000100000 ,
b100110000100000 6
b1001100001000000 8
1'
#50
0'
#55
b101 3
b100 4
b10011000010000 !
b10011000010000 ,
b10011000010000 6
b100110000100000 8
1'
#60
0'
#65
b10 3
b101 4
b11111010001000 !
b11111010001000 ,
b11111010001000 6
b111110100010000 8
1'
#70
0'
#75
b1 3
b110 4
b1111101000100 !
b1111101000100 ,
b1111101000100 6
b11111010001000 8
1'
#80
0'
#85
b0 3
b111 4
b11101100100010 !
b11101100100010 ,
b11101100100010 6
b111011001000100 8
1'
#90
0'
#95
b11 5
b1000 4
b1110110010001 !
b1110110010001 ,
b1110110010001 6
b11101100100010 8
1'
#100
0'
#105
b0 5
1"
b11 7
1'
#110
0'
#115
0"
b0 7
1'
